README.md
setup.cfg
setup.py
datadog_http_handler/__init__.py
datadog_http_handler.egg-info/PKG-INFO
datadog_http_handler.egg-info/SOURCES.txt
datadog_http_handler.egg-info/dependency_links.txt
datadog_http_handler.egg-info/not-zip-safe
datadog_http_handler.egg-info/requires.txt
datadog_http_handler.egg-info/top_level.txt