Metadata-Version: 1.1
Name: datadog-http-handler
Version: 1.0.7
Summary: Python logging module allowing you to log directly to Datadog via https
Home-page: https://github.com/nrccua/datadog-http-handler
Author: NRCCUA Architects
Author-email: architecture@nrccua.org
License: MIT
Platform: UNKNOWN
Classifier: Programming Language :: Python :: 3
Classifier: License :: OSI Approved :: MIT License
Classifier: Operating System :: OS Independent
